setup.py
jaka_data_collection/__init__.py
jaka_data_collection/jaka_data_collection.py
jaka_data_collection.egg-info/PKG-INFO
jaka_data_collection.egg-info/SOURCES.txt
jaka_data_collection.egg-info/dependency_links.txt
jaka_data_collection.egg-info/top_level.txt