Metadata-Version: 2.1
Name: jaka-data-collection
Version: 0.1
Summary: A library for data collection using Jaka robots
Author: Zhao SiJie
